BBI/__init__.py
BBI/core.py
bac_info/__init__.py
bac_info/core.py
bac_info-0.0.4.dist-info/licenses/LICENSE
bac_info-0.0.4.dist-info/METADATA
bac_info-0.0.4.dist-info/WHEEL
bac_info-0.0.4.dist-info/top_level.txt
bac_info-0.0.4.dist-info/RECORD
