Metadata-Version: 2.4
Name: Bac_info
Version: 0.0.4
Summary: A collection of utility functions for common programming tasks including input validation, array/matrix operations, string processing, and mathematical calculations.
Home-page: 
Author: Aziz boudriga
Author-email: 
License: MIT
Classifier: Programming Language :: Python :: 3
Classifier: License :: OSI Approved :: MIT License
Classifier: Operating System :: OS Independent
Requires-Python: >=3.6
License-File: LICENSE
Dynamic: author
Dynamic: classifier
Dynamic: description
Dynamic: description-content-type
Dynamic: license
Dynamic: license-file
Dynamic: requires-python
Dynamic: summary
